ufds/__init__.py
ufds/_version.py
ufds/disjoint_set.py
ufds/native_base.py
ufds-0.2.1.dist-info/LICENSE
ufds-0.2.1.dist-info/METADATA
ufds-0.2.1.dist-info/WHEEL
ufds-0.2.1.dist-info/top_level.txt
ufds-0.2.1.dist-info/RECORD
