Metadata-Version: 2.1
Name: ufds
Version: 0.2.1
Summary: Union-Find (Disjoint Set) Data Structure
Author-email: Louis Cochen <louis.cochen@protonmail.ch>
Maintainer-email: Louis Cochen <louis.cochen@protonmail.ch>
License: 
Project-URL: Homepage, https://gitlab.com/ljmc/ufds
Project-URL: Bug Tracker, https://gitlab.com/ljmc/ufds/-/issues
Classifier: Development Status :: 4 - Beta
Classifier: Intended Audience :: Developers
Classifier: License :: OSI Approved :: Apache Software License
Classifier: Natural Language :: English
Classifier: Operating System :: OS Independent
Classifier: Programming Language :: Python
Classifier: Programming Language :: Python :: 3
Classifier: Programming Language :: Python :: 3.8
Classifier: Programming Language :: Python :: 3.9
Classifier: Programming Language :: Python :: 3.10
Classifier: Programming Language :: Python :: 3.11
Requires-Python: >=3.8
License-File: LICENSE
